Workbook

Sheet Resumen
A1: Análisis Exploratorio de Datos — Frutería
A2: Resumen de hallazgos clave (calculado automáticamente a partir de Datos_Originales)
A4: Indicador | B4: Valor
A5: Total invertido (todas las frutas) | B5: =SUM(Datos_Originales!$B$5:$B$16) -> 42
A6: Total vendido (Total) | B6: =SUM(Datos_Originales!$H$5:$H$16) -> 74
A7: Ganancia neta (Venta - Inversión) | B7: =SUM(Datos_Originales!$H$5:$H$16)-SUM(Datos_Originales!$B$5:$B$16) -> 32
A8: N° de frutas registradas | B8: =COUNTA(Datos_Originales!$A$5:$A$16) -> 12
A9: N° de frutas SIN venta (comprador vacío) | B9: =COUNTBLANK(Datos_Originales!$G$5:$G$16) -> 2
A10: Fruta con mayor inversión | B10: =INDEX(Datos_Originales!$A$5:$A$16,MATCH(MAX(Datos_Originales!$B$5:$B$16),Datos_Originales!$B$5:$B$16,0)) -> Sandía
A11: Fruta con mayor Total vendido | B11: =INDEX(Datos_Originales!$A$5:$A$16,MATCH(MAX(Datos_Originales!$H$5:$H$16),Datos_Originales!$H$5:$H$16,0)) -> Papaya
A12: Ronda más rentable | B12: =INDEX(Analisis_Rondas!$A$4:$A$6,MATCH(MAX(Analisis_Rondas!$D$4:$D$6),Analisis_Rondas!$D$4:$D$6,0)) -> 1
A13: Comprador que más gastó | B13: =INDEX(Analisis_Comprador!$A$4:$A$10,MATCH(MAX(Analisis_Comprador!$B$4:$B$10),Analisis_Comprador!$B$4:$B$10,0)) -> Antwone
A16: Ver hojas: Datos_Originales, Valores_Faltantes, Estadisticas_Descriptivas, Analisis_Rondas, Analisis_Comprador, Graficos

Sheet Datos_Originales
A1: Datos originales — Frutería
A2: Fuente: fruteria_inge_de_datos.xlsx (Hoja 1). Copiado sin modificar para trazabilidad del análisis.
A4: Frutas | B4: Inversión (MIL) | C4: Precio en K | D4: Precio de ganancia en K | E4: Ganancia | F4: Cantidad | G4: Nombre del comprador | H4: Total | I4: Ronda
A5: Pera | B5: 2 | C5: 2.5 | F5: 1 | G5: Juan Esteban | H5: 2.5 | I5: 2
A6: Piña | B6: 4 | C6: 6 | D6: 8 | F6: 1 | G6: David | H6: 8 | I6: 3
A7: Papaya | B7: 4 | C7: 6 | F7: 3 | G7: Antwone | H7: 18 | I7: 1
A8: Sandía | B8: 6 | C8: 8 | H8: 0
A9: Manzana | B9: 2 | C9: 3.5 | F9: 1 | G9: Sara | H9: 3.5 | I9: 1
A10: Banano | B10: 1 | C10: 4 | F10: 1 | G10: Antwone | H10: 4 | I10: 1
A11: Uva | B11: 6 | C11: 9 | D11: 10 | F11: 1 | G11: Lina | H11: 10 | I11: 3
A12: Naranja | B12: 2 | C12: 3 | H12: 0
A13: Lima | B13: 1 | C13: 2 | F13: 2 | G13: Mariana | H13: 4 | I13: 2
A14: Pitahaya | B14: 5 | C14: 8 | F14: 1 | G14: Antwone | H14: 8 | I14: 1
A15: Cereza | B15: 4 | C15: 6 | F15: 1 | G15: Alisson | H15: 6 | I15: 3
A16: Arándanos | B16: 5 | C16: 8 | D16: 10 | F16: 1 | G16: David | H16: 10 | I16: 3

Sheet Valores_Faltantes
A1: Análisis de valores faltantes
A2: Total de filas de datos: 12
A4: Columna | B4: Valores presentes | C4: Valores nulos | D4: % Nulos
A5: Frutas | B5: =COUNTA(Datos_Originales!$A$5:$A$16) -> 12 | C5: =12-B5 -> 0 | D5: =C5/12 -> 0
A6: Inversión (MIL) | B6: =COUNT(Datos_Originales!$B$5:$B$16) -> 12 | C6: =12-B6 -> 0 | D6: =C6/12 -> 0
A7: Precio en K | B7: =COUNT(Datos_Originales!$C$5:$C$16) -> 12 | C7: =12-B7 -> 0 | D7: =C7/12 -> 0
A8: Precio de ganancia en K | B8: =COUNT(Datos_Originales!$D$5:$D$16) -> 3 | C8: =12-B8 -> 9 | D8: =C8/12 -> 0.75
A9: Ganancia | B9: =COUNT(Datos_Originales!$E$5:$E$16) -> 0 | C9: =12-B9 -> 12 | D9: =C9/12 -> 1
A10: Cantidad | B10: =COUNT(Datos_Originales!$F$5:$F$16) -> 10 | C10: =12-B10 -> 2 | D10: =C10/12 -> 0.16666667
A11: Nombre del comprador | B11: =COUNTA(Datos_Originales!$G$5:$G$16) -> 10 | C11: =12-B11 -> 2 | D11: =C11/12 -> 0.16666667
A12: Total | B12: =COUNT(Datos_Originales!$H$5:$H$16) -> 12 | C12: =12-B12 -> 0 | D12: =C12/12 -> 0
A13: Ronda | B13: =COUNT(Datos_Originales!$I$5:$I$16) -> 10 | C13: =12-B13 -> 2 | D13: =C13/12 -> 0.16666667
A15: Nota: 'Ganancia' está vacía en el 100% de las filas; 'Precio de ganancia en K' solo se registró cuando el precio de venta difirió del precio de lista.

Sheet Estadisticas_Descriptivas
A1: Estadística descriptiva (columnas numéricas)
A3: Métrica | B3: Inversión (MIL) | C3: Precio en K | D3: Cantidad | E3: Total
A4: N (conteo) | B4: =COUNT(Datos_Originales!$B$5:$B$16) -> 12 | C4: =COUNT(Datos_Originales!$C$5:$C$16) -> 12 | D4: =COUNT(Datos_Originales!$F$5:$F$16) -> 10 | E4: =COUNT(Datos_Originales!$H$5:$H$16) -> 12
A5: Mínimo | B5: =MIN(Datos_Originales!$B$5:$B$16) -> 1 | C5: =MIN(Datos_Originales!$C$5:$C$16) -> 2 | D5: =MIN(Datos_Originales!$F$5:$F$16) -> 1 | E5: =MIN(Datos_Originales!$H$5:$H$16) -> 0
A6: Máximo | B6: =MAX(Datos_Originales!$B$5:$B$16) -> 6 | C6: =MAX(Datos_Originales!$C$5:$C$16) -> 9 | D6: =MAX(Datos_Originales!$F$5:$F$16) -> 3 | E6: =MAX(Datos_Originales!$H$5:$H$16) -> 18
A7: Promedio | B7: =AVERAGE(Datos_Originales!$B$5:$B$16) -> 3.5 | C7: =AVERAGE(Datos_Originales!$C$5:$C$16) -> 5.5 | D7: =AVERAGE(Datos_Originales!$F$5:$F$16) -> 1.3 | E7: =AVERAGE(Datos_Originales!$H$5:$H$16) -> 6.1666667
A8: Mediana | B8: =MEDIAN(Datos_Originales!$B$5:$B$16) -> 4 | C8: =MEDIAN(Datos_Originales!$C$5:$C$16) -> 6 | D8: =MEDIAN(Datos_Originales!$F$5:$F$16) -> 1 | E8: =MEDIAN(Datos_Originales!$H$5:$H$16) -> 5
A9: Desviación estándar | B9: =_xlfn.STDEV.S(Datos_Originales!$B$5:$B$16) -> 1.8340219 | C9: =_xlfn.STDEV.S(Datos_Originales!$C$5:$C$16) -> 2.4401937 | D9: =_xlfn.STDEV.S(Datos_Originales!$F$5:$F$16) -> 0.67494856 | E9: =_xlfn.STDEV.S(Datos_Originales!$H$5:$H$16) -> 5.0647325
A10: Suma | B10: =SUM(Datos_Originales!$B$5:$B$16) -> 42 | C10: =SUM(Datos_Originales!$C$5:$C$16) -> 66 | D10: =SUM(Datos_Originales!$F$5:$F$16) -> 13 | E10: =SUM(Datos_Originales!$H$5:$H$16) -> 74

Sheet Analisis_Rondas
A1: Análisis por ronda
A3: Ronda | B3: Gasto (Inversión) | C3: Venta (Total) | D3: Ganancia neta | E3: N° frutas vendidas
A4: 1 | B4: =SUMIF(Datos_Originales!$I$5:$I$16,A4,Datos_Originales!$B$5:$B$16) -> 12 | C4: =SUMIF(Datos_Originales!$I$5:$I$16,A4,Datos_Originales!$H$5:$H$16) -> 33.5 | D4: =C4-B4 -> 21.5 | E4: =COUNTIF(Datos_Originales!$I$5:$I$16,A4) -> 4
A5: 2 | B5: =SUMIF(Datos_Originales!$I$5:$I$16,A5,Datos_Originales!$B$5:$B$16) -> 3 | C5: =SUMIF(Datos_Originales!$I$5:$I$16,A5,Datos_Originales!$H$5:$H$16) -> 6.5 | D5: =C5-B5 -> 3.5 | E5: =COUNTIF(Datos_Originales!$I$5:$I$16,A5) -> 2
A6: 3 | B6: =SUMIF(Datos_Originales!$I$5:$I$16,A6,Datos_Originales!$B$5:$B$16) -> 19 | C6: =SUMIF(Datos_Originales!$I$5:$I$16,A6,Datos_Originales!$H$5:$H$16) -> 34 | D6: =C6-B6 -> 15 | E6: =COUNTIF(Datos_Originales!$I$5:$I$16,A6) -> 4
A7: Total | B7: =SUM(B4:B6) -> 34 | C7: =SUM(C4:C6) -> 74 | D7: =SUM(D4:D6) -> 40 | E7: =SUM(E4:E6) -> 10

Sheet Analisis_Comprador
A1: Análisis por comprador
A3: Comprador | B3: Total gastado | C3: N° compras
A4: Juan Esteban | B4: =SUMIF(Datos_Originales!$G$5:$G$16,A4,Datos_Originales!$H$5:$H$16) -> 2.5 | C4: =COUNTIF(Datos_Originales!$G$5:$G$16,A4) -> 1
A5: David | B5: =SUMIF(Datos_Originales!$G$5:$G$16,A5,Datos_Originales!$H$5:$H$16) -> 18 | C5: =COUNTIF(Datos_Originales!$G$5:$G$16,A5) -> 2
A6: Antwone | B6: =SUMIF(Datos_Originales!$G$5:$G$16,A6,Datos_Originales!$H$5:$H$16) -> 30 | C6: =COUNTIF(Datos_Originales!$G$5:$G$16,A6) -> 3
A7: Sara | B7: =SUMIF(Datos_Originales!$G$5:$G$16,A7,Datos_Originales!$H$5:$H$16) -> 3.5 | C7: =COUNTIF(Datos_Originales!$G$5:$G$16,A7) -> 1
A8: Lina | B8: =SUMIF(Datos_Originales!$G$5:$G$16,A8,Datos_Originales!$H$5:$H$16) -> 10 | C8: =COUNTIF(Datos_Originales!$G$5:$G$16,A8) -> 1
A9: Mariana | B9: =SUMIF(Datos_Originales!$G$5:$G$16,A9,Datos_Originales!$H$5:$H$16) -> 4 | C9: =COUNTIF(Datos_Originales!$G$5:$G$16,A9) -> 1
A10: Alisson | B10: =SUMIF(Datos_Originales!$G$5:$G$16,A10,Datos_Originales!$H$5:$H$16) -> 6 | C10: =COUNTIF(Datos_Originales!$G$5:$G$16,A10) -> 1

Sheet Graficos
A1: Visualizaciones
